modoboa_dmarc/__init__.py
modoboa_dmarc/admin.py
modoboa_dmarc/apps.py
modoboa_dmarc/constants.py
modoboa_dmarc/forms.py
modoboa_dmarc/handlers.py
modoboa_dmarc/lib.py
modoboa_dmarc/models.py
modoboa_dmarc/modo_extension.py
modoboa_dmarc/urls.py
modoboa_dmarc/views.py
modoboa_dmarc/locale/br/LC_MESSAGES/django.mo
modoboa_dmarc/locale/br/LC_MESSAGES/django.po
modoboa_dmarc/locale/cs_CZ/LC_MESSAGES/django.mo
modoboa_dmarc/locale/cs_CZ/LC_MESSAGES/django.po
modoboa_dmarc/locale/de/LC_MESSAGES/django.mo
modoboa_dmarc/locale/de/LC_MESSAGES/django.po
modoboa_dmarc/locale/el_GR/LC_MESSAGES/django.mo
modoboa_dmarc/locale/el_GR/LC_MESSAGES/django.po
modoboa_dmarc/locale/en/LC_MESSAGES/django.mo
modoboa_dmarc/locale/en/LC_MESSAGES/django.po
modoboa_dmarc/locale/fr/LC_MESSAGES/django.mo
modoboa_dmarc/locale/fr/LC_MESSAGES/django.po
modoboa_dmarc/locale/it/LC_MESSAGES/django.mo
modoboa_dmarc/locale/it/LC_MESSAGES/django.po
modoboa_dmarc/locale/ja_JP/LC_MESSAGES/django.mo
modoboa_dmarc/locale/ja_JP/LC_MESSAGES/django.po
modoboa_dmarc/locale/nl_NL/LC_MESSAGES/django.mo
modoboa_dmarc/locale/nl_NL/LC_MESSAGES/django.po
modoboa_dmarc/locale/pt_BR/LC_MESSAGES/django.mo
modoboa_dmarc/locale/pt_BR/LC_MESSAGES/django.po
modoboa_dmarc/locale/sv/LC_MESSAGES/django.mo
modoboa_dmarc/locale/sv/LC_MESSAGES/django.po
modoboa_dmarc/management/__init__.py
modoboa_dmarc/management/commands/__init__.py
modoboa_dmarc/management/commands/import_aggregated_report.py
modoboa_dmarc/migrations/0001_initial.py
modoboa_dmarc/migrations/0002_auto_20180124_2311.py
modoboa_dmarc/migrations/0003_auto_20200227_0936.py
modoboa_dmarc/migrations/__init__.py
modoboa_dmarc/templates/modoboa_dmarc/_result_detail.html
modoboa_dmarc/templates/modoboa_dmarc/domain_report.html
modoboa_dmarc/templatetags/__init__.py
modoboa_dmarc/templatetags/dmarc_tags.py
modoboa_dmarc/tests/__init__.py
modoboa_dmarc/tests/mixins.py
modoboa_dmarc/tests/test_management_command.py
modoboa_dmarc/tests/test_views.py
modoboa_dmarc-1.3.0.dist-info/LICENSE
modoboa_dmarc-1.3.0.dist-info/METADATA
modoboa_dmarc-1.3.0.dist-info/WHEEL
modoboa_dmarc-1.3.0.dist-info/top_level.txt
modoboa_dmarc-1.3.0.dist-info/RECORD
